seededturtle/__init__.py
seededturtle/randturtle.py
seededturtle-1.0.2.dist-info/METADATA
seededturtle-1.0.2.dist-info/WHEEL
seededturtle-1.0.2.dist-info/licenses/LICENSE
seededturtle-1.0.2.dist-info/RECORD
