Metadata-Version: 2.3
Name: SeededTurtle
Version: 1.0.2
Summary: A python library for generating random turtles using a hash seed (and for generating seeds/colors)
Project-URL: Homepage, https://github.com/Ruxton07/SeededTurtle
Project-URL: Issues, https://github.com/Ruxton07/SeededTurtle/issues
Author-email: Ruxton <rt.kellar@gmail.com>
License-File: LICENSE
Classifier: License :: OSI Approved :: MIT License
Classifier: Operating System :: OS Independent
Classifier: Programming Language :: Python :: 3
Requires-Python: >=3.8
